{
  "BTCUSDT": {
    "correlation": 0.12166014710359475,
    "abs_correlation": 0.12166014710359475,
    "data_points": 7,
    "volume_increase_on_price_up_pct": 100.0,
    "avg_volume_change_on_price_up": 35.06599516824851
  },
  "ETHUSDT": {
    "correlation": 0.37665240784025167,
    "abs_correlation": 0.37665240784025167,
    "data_points": 7,
    "volume_increase_on_price_up_pct": 66.66666666666666,
    "avg_volume_change_on_price_up": 8.248591429011041
  },
  "USDTUSDT": {
    "correlation": 0.41678327073242666,
    "abs_correlation": 0.41678327073242666,
    "data_points": 7,
    "volume_increase_on_price_up_pct": 75.0,
    "avg_volume_change_on_price_up": 6.493168232580429
  },
  "XRPUSDT": {
    "correlation": 0.4333578314027553,
    "abs_correlation": 0.4333578314027553,
    "data_points": 7,
    "volume_increase_on_price_up_pct": 50.0,
    "avg_volume_change_on_price_up": 7.911076282578095
  },
  "BNBUSDT": {
    "correlation": -0.13297703284918377,
    "abs_correlation": 0.13297703284918377,
    "data_points": 7,
    "volume_increase_on_price_up_pct": 33.33333333333333,
    "avg_volume_change_on_price_up": -7.399048658945169
  },
  "SOLUSDT": {
    "correlation": 0.4410146573600625,
    "abs_correlation": 0.4410146573600625,
    "data_points": 7,
    "volume_increase_on_price_up_pct": 100.0,
    "avg_volume_change_on_price_up": 32.180569900387646
  },
  "USDCUSDT": {
    "correlation": 0.5625231308428502,
    "abs_correlation": 0.5625231308428502,
    "data_points": 7,
    "volume_increase_on_price_up_pct": 25.0,
    "avg_volume_change_on_price_up": 4.887641401885104
  },
  "TRXUSDT": {
    "correlation": -0.19749915862560752,
    "abs_correlation": 0.19749915862560752,
    "data_points": 7,
    "volume_increase_on_price_up_pct": 0.0,
    "avg_volume_change_on_price_up": -32.12186265475565
  },
  "STETHUSDT": {
    "correlation": -0.09509392882169429,
    "abs_correlation": 0.09509392882169429,
    "data_points": 7,
    "volume_increase_on_price_up_pct": 33.33333333333333,
    "avg_volume_change_on_price_up": -21.389901889274203
  },
  "DOGEUSDT": {
    "correlation": -0.1372267276126851,
    "abs_correlation": 0.1372267276126851,
    "data_points": 7,
    "volume_increase_on_price_up_pct": 33.33333333333333,
    "avg_volume_change_on_price_up": -9.607698897078711
  },
  "ADAUSDT": {
    "correlation": -0.009506037382854982,
    "abs_correlation": 0.009506037382854982,
    "data_points": 7,
    "volume_increase_on_price_up_pct": 100.0,
    "avg_volume_change_on_price_up": 17.33695542287903
  },
  "FIGR_HELOCUSDT": {
    "correlation": 0.09878972398359868,
    "abs_correlation": 0.09878972398359868,
    "data_points": 7,
    "volume_increase_on_price_up_pct": 50.0,
    "avg_volume_change_on_price_up": 52.3315773930781
  },
  "WBTUSDT": {
    "correlation": 0.3195232822476394,
    "abs_correlation": 0.3195232822476394,
    "data_points": 7,
    "volume_increase_on_price_up_pct": 100.0,
    "avg_volume_change_on_price_up": 32.30618335076528
  },
  "WSTETHUSDT": {
    "correlation": -0.04709762761212061,
    "abs_correlation": 0.04709762761212061,
    "data_points": 7,
    "volume_increase_on_price_up_pct": 66.66666666666666,
    "avg_volume_change_on_price_up": -11.70130894703204
  },
  "WBTCUSDT": {
    "correlation": -0.04907367978766584,
    "abs_correlation": 0.04907367978766584,
    "data_points": 7,
    "volume_increase_on_price_up_pct": 100.0,
    "avg_volume_change_on_price_up": 17.979705835966275
  },
  "BCHUSDT": {
    "correlation": 0.8690638532440238,
    "abs_correlation": 0.8690638532440238,
    "data_points": 7,
    "volume_increase_on_price_up_pct": 33.33333333333333,
    "avg_volume_change_on_price_up": 32.65420724890482
  },
  "WBETHUSDT": {
    "correlation": 0.7280998876137659,
    "abs_correlation": 0.7280998876137659,
    "data_points": 7,
    "volume_increase_on_price_up_pct": 66.66666666666666,
    "avg_volume_change_on_price_up": 158.75480258370783
  },
  "USDSUSDT": {
    "correlation": 0.3135176527472783,
    "abs_correlation": 0.3135176527472783,
    "data_points": 7,
    "volume_increase_on_price_up_pct": 75.0,
    "avg_volume_change_on_price_up": 234.64210261723943
  },
  "LINKUSDT": {
    "correlation": -0.21151179117605082,
    "abs_correlation": 0.21151179117605082,
    "data_points": 7,
    "volume_increase_on_price_up_pct": 66.66666666666666,
    "avg_volume_change_on_price_up": -8.265705140753138
  },
  "BSC-USDUSDT": {
    "correlation": -0.5575851782424007,
    "abs_correlation": 0.5575851782424007,
    "data_points": 7,
    "volume_increase_on_price_up_pct": 25.0,
    "avg_volume_change_on_price_up": -9.048081298875084
  },
  "LEOUSDT": {
    "correlation": 0.11774953705215296,
    "abs_correlation": 0.11774953705215296,
    "data_points": 7,
    "volume_increase_on_price_up_pct": 50.0,
    "avg_volume_change_on_price_up": 25.15893461074504
  },
  "HYPEUSDT": {
    "correlation": -0.21918446707155903,
    "abs_correlation": 0.21918446707155903,
    "data_points": 7,
    "volume_increase_on_price_up_pct": 50.0,
    "avg_volume_change_on_price_up": 1.4412482707866083
  },
  "ZECUSDT": {
    "correlation": -0.6308706508439227,
    "abs_correlation": 0.6308706508439227,
    "data_points": 7,
    "volume_increase_on_price_up_pct": 0.0,
    "avg_volume_change_on_price_up": -25.764770338518872
  },
  "XLMUSDT": {
    "correlation": 0.3678976694035116,
    "abs_correlation": 0.3678976694035116,
    "data_points": 7,
    "volume_increase_on_price_up_pct": 100.0,
    "avg_volume_change_on_price_up": 40.3237396476838
  },
  "WETHUSDT": {
    "correlation": 0.3206932926876785,
    "abs_correlation": 0.3206932926876785,
    "data_points": 7,
    "volume_increase_on_price_up_pct": 66.66666666666666,
    "avg_volume_change_on_price_up": 3.3753914780142225
  },
  "WEETHUSDT": {
    "correlation": 0.3052237913368158,
    "abs_correlation": 0.3052237913368158,
    "data_points": 7,
    "volume_increase_on_price_up_pct": 66.66666666666666,
    "avg_volume_change_on_price_up": 134.46637467878702
  },
  "USDEUSDT": {
    "correlation": 0.4163125155947515,
    "abs_correlation": 0.4163125155947515,
    "data_points": 7,
    "volume_increase_on_price_up_pct": 33.33333333333333,
    "avg_volume_change_on_price_up": 6.301761495210008
  },
  "XMRUSDT": {
    "correlation": -0.0803932267362726,
    "abs_correlation": 0.0803932267362726,
    "data_points": 7,
    "volume_increase_on_price_up_pct": 66.66666666666666,
    "avg_volume_change_on_price_up": 2.4660075688118575
  },
  "LTCUSDT": {
    "correlation": -0.20019379483420882,
    "abs_correlation": 0.20019379483420882,
    "data_points": 7,
    "volume_increase_on_price_up_pct": 100.0,
    "avg_volume_change_on_price_up": 12.564009998458895
  },
  "CBBTCUSDT": {
    "correlation": 0.12695909178783385,
    "abs_correlation": 0.12695909178783385,
    "data_points": 7,
    "volume_increase_on_price_up_pct": 100.0,
    "avg_volume_change_on_price_up": 41.10485378366941
  },
  "HBARUSDT": {
    "correlation": 0.7290269717387229,
    "abs_correlation": 0.7290269717387229,
    "data_points": 7,
    "volume_increase_on_price_up_pct": 33.33333333333333,
    "avg_volume_change_on_price_up": 33.943132456259164
  },
  "AVAXUSDT": {
    "correlation": 0.26023804131741685,
    "abs_correlation": 0.26023804131741685,
    "data_points": 7,
    "volume_increase_on_price_up_pct": 33.33333333333333,
    "avg_volume_change_on_price_up": 8.851505568854169
  },
  "SUIUSDT": {
    "correlation": 0.4309975091100349,
    "abs_correlation": 0.4309975091100349,
    "data_points": 7,
    "volume_increase_on_price_up_pct": 33.33333333333333,
    "avg_volume_change_on_price_up": 29.130917089012502
  },
  "SHIBUSDT": {
    "correlation": -0.027284339057183162,
    "abs_correlation": 0.027284339057183162,
    "data_points": 7,
    "volume_increase_on_price_up_pct": 50.0,
    "avg_volume_change_on_price_up": 14.441957892383353
  },
  "DAIUSDT": {
    "correlation": 0.09027342145881292,
    "abs_correlation": 0.09027342145881292,
    "data_points": 7,
    "volume_increase_on_price_up_pct": 66.66666666666666,
    "avg_volume_change_on_price_up": 38.01577682328659
  },
  "WLFIUSDT": {
    "correlation": 0.6771985056787395,
    "abs_correlation": 0.6771985056787395,
    "data_points": 7,
    "volume_increase_on_price_up_pct": 40.0,
    "avg_volume_change_on_price_up": 34.224602393607384
  },
  "SUSDEUSDT": {
    "correlation": -0.07107118922064515,
    "abs_correlation": 0.07107118922064515,
    "data_points": 7,
    "volume_increase_on_price_up_pct": 40.0,
    "avg_volume_change_on_price_up": -8.023016402289752
  },
  "CROUSDT": {
    "correlation": 0.4432576419747426,
    "abs_correlation": 0.4432576419747426,
    "data_points": 7,
    "volume_increase_on_price_up_pct": 33.33333333333333,
    "avg_volume_change_on_price_up": 15.815625326216095
  },
  "UNIUSDT": {
    "correlation": 0.544494631612444,
    "abs_correlation": 0.544494631612444,
    "data_points": 7,
    "volume_increase_on_price_up_pct": 100.0,
    "avg_volume_change_on_price_up": 47.952632131156435
  },
  "USDT0USDT": {
    "correlation": 0.5867016123001491,
    "abs_correlation": 0.5867016123001491,
    "data_points": 7,
    "volume_increase_on_price_up_pct": 66.66666666666666,
    "avg_volume_change_on_price_up": 16.29268278176685
  },
  "SUSDSUSDT": {
    "correlation": 0.7128273316173293,
    "abs_correlation": 0.7128273316173293,
    "data_points": 7,
    "volume_increase_on_price_up_pct": 100.0,
    "avg_volume_change_on_price_up": 1695.7590954309378
  },
  "DOTUSDT": {
    "correlation": 0.06348620138714176,
    "abs_correlation": 0.06348620138714176,
    "data_points": 7,
    "volume_increase_on_price_up_pct": 100.0,
    "avg_volume_change_on_price_up": 41.876999141804895
  },
  "TONUSDT": {
    "correlation": -0.09931013630709733,
    "abs_correlation": 0.09931013630709733,
    "data_points": 7,
    "volume_increase_on_price_up_pct": 50.0,
    "avg_volume_change_on_price_up": -10.007508067485515
  },
  "PYUSDUSDT": {
    "correlation": 0.6252307290926917,
    "abs_correlation": 0.6252307290926917,
    "data_points": 7,
    "volume_increase_on_price_up_pct": 50.0,
    "avg_volume_change_on_price_up": 15.756930988970586
  },
  "MNTUSDT": {
    "correlation": -0.7666122068820168,
    "abs_correlation": 0.7666122068820168,
    "data_points": 7,
    "volume_increase_on_price_up_pct": 25.0,
    "avg_volume_change_on_price_up": -10.242885330699313
  },
  "CCUSDT": {
    "correlation": 0.1522085377518801,
    "abs_correlation": 0.1522085377518801,
    "data_points": 7,
    "volume_increase_on_price_up_pct": 50.0,
    "avg_volume_change_on_price_up": 181.55213308078467
  },
  "MUSDT": {
    "correlation": 0.37387000656812663,
    "abs_correlation": 0.37387000656812663,
    "data_points": 7,
    "volume_increase_on_price_up_pct": 100.0,
    "avg_volume_change_on_price_up": 2.2512827099741606
  },
  "TAOUSDT": {
    "correlation": 0.27413122466583884,
    "abs_correlation": 0.27413122466583884,
    "data_points": 7,
    "volume_increase_on_price_up_pct": 100.0,
    "avg_volume_change_on_price_up": 64.36088080120297
  },
  "AAVEUSDT": {
    "correlation": 0.07898608115955325,
    "abs_correlation": 0.07898608115955325,
    "data_points": 7,
    "volume_increase_on_price_up_pct": 50.0,
    "avg_volume_change_on_price_up": -2.447294826532681
  },
  "USD1USDT": {
    "correlation": 0.8521753126567763,
    "abs_correlation": 0.8521753126567763,
    "data_points": 7,
    "volume_increase_on_price_up_pct": 100.0,
    "avg_volume_change_on_price_up": 10.351779674325805
  },
  "BGBUSDT": {
    "correlation": -0.7888310255071549,
    "abs_correlation": 0.7888310255071549,
    "data_points": 7,
    "volume_increase_on_price_up_pct": 25.0,
    "avg_volume_change_on_price_up": -11.99985889319428
  },
  "NEARUSDT": {
    "correlation": 0.2131149090214299,
    "abs_correlation": 0.2131149090214299,
    "data_points": 7,
    "volume_increase_on_price_up_pct": 33.33333333333333,
    "avg_volume_change_on_price_up": 16.491132411643893
  },
  "ASTERUSDT": {
    "correlation": -0.06421076766807607,
    "abs_correlation": 0.06421076766807607,
    "data_points": 7,
    "volume_increase_on_price_up_pct": 50.0,
    "avg_volume_change_on_price_up": -1.7092562050640052
  },
  "BUIDLUSDT": {
    "correlation": 0.0,
    "abs_correlation": 0.0,
    "data_points": 7,
    "volume_increase_on_price_up_pct": 0.0,
    "avg_volume_change_on_price_up": 0.0
  },
  "ICPUSDT": {
    "correlation": 0.5934319044852662,
    "abs_correlation": 0.5934319044852662,
    "data_points": 7,
    "volume_increase_on_price_up_pct": 50.0,
    "avg_volume_change_on_price_up": 17.205213858807355
  },
  "OKBUSDT": {
    "correlation": -0.62215115275452,
    "abs_correlation": 0.62215115275452,
    "data_points": 7,
    "volume_increase_on_price_up_pct": 0.0,
    "avg_volume_change_on_price_up": -22.02211189954464
  },
  "USDFUSDT": {
    "correlation": 0.007076761544138115,
    "abs_correlation": 0.007076761544138115,
    "data_points": 7,
    "volume_increase_on_price_up_pct": 100.0,
    "avg_volume_change_on_price_up": 130.93649230058767
  },
  "ETCUSDT": {
    "correlation": 0.24081387725467782,
    "abs_correlation": 0.24081387725467782,
    "data_points": 7,
    "volume_increase_on_price_up_pct": 66.66666666666666,
    "avg_volume_change_on_price_up": 18.194844405889725
  },
  "XAUTUSDT": {
    "correlation": 0.6217566828692984,
    "abs_correlation": 0.6217566828692984,
    "data_points": 7,
    "volume_increase_on_price_up_pct": 75.0,
    "avg_volume_change_on_price_up": 16.220590880525435
  },
  "PIUSDT": {
    "correlation": 0.5413109978761248,
    "abs_correlation": 0.5413109978761248,
    "data_points": 7,
    "volume_increase_on_price_up_pct": 50.0,
    "avg_volume_change_on_price_up": 23.272839935493277
  },
  "ENAUSDT": {
    "correlation": 0.5641559322167079,
    "abs_correlation": 0.5641559322167079,
    "data_points": 7,
    "volume_increase_on_price_up_pct": 66.66666666666666,
    "avg_volume_change_on_price_up": 25.127727714583443
  },
  "JITOSOLUSDT": {
    "correlation": 0.2770626753217969,
    "abs_correlation": 0.2770626753217969,
    "data_points": 7,
    "volume_increase_on_price_up_pct": 50.0,
    "avg_volume_change_on_price_up": 21.268376861494264
  },
  "PEPEUSDT": {
    "correlation": -0.07779787118818482,
    "abs_correlation": 0.07779787118818482,
    "data_points": 7,
    "volume_increase_on_price_up_pct": 33.33333333333333,
    "avg_volume_change_on_price_up": -7.428004227500582
  },
  "RAINUSDT": {
    "correlation": 0.9885479540033167,
    "abs_correlation": 0.9885479540033167,
    "data_points": 7,
    "volume_increase_on_price_up_pct": 75.0,
    "avg_volume_change_on_price_up": 143.00989581284705
  },
  "JLPUSDT": {
    "correlation": 0.12193030410986415,
    "abs_correlation": 0.12193030410986415,
    "data_points": 7,
    "volume_increase_on_price_up_pct": 50.0,
    "avg_volume_change_on_price_up": 27.951789042721586
  },
  "APTUSDT": {
    "correlation": -0.7136815161977366,
    "abs_correlation": 0.7136815161977366,
    "data_points": 7,
    "volume_increase_on_price_up_pct": 50.0,
    "avg_volume_change_on_price_up": -5.076745555792145
  },
  "PUMPUSDT": {
    "correlation": -0.043404692906512214,
    "abs_correlation": 0.043404692906512214,
    "data_points": 7,
    "volume_increase_on_price_up_pct": 50.0,
    "avg_volume_change_on_price_up": -2.4463527225397836
  },
  "HTXUSDT": {
    "correlation": -0.6338533143349167,
    "abs_correlation": 0.6338533143349167,
    "data_points": 7,
    "volume_increase_on_price_up_pct": 0.0,
    "avg_volume_change_on_price_up": -2.187329689967606
  },
  "ONDOUSDT": {
    "correlation": -0.22327523403438043,
    "abs_correlation": 0.22327523403438043,
    "data_points": 7,
    "volume_increase_on_price_up_pct": 50.0,
    "avg_volume_change_on_price_up": 9.531523467575814
  },
  "KCSUSDT": {
    "correlation": 0.4452844280609956,
    "abs_correlation": 0.4452844280609956,
    "data_points": 7,
    "volume_increase_on_price_up_pct": 66.66666666666666,
    "avg_volume_change_on_price_up": 21.601402179425698
  },
  "WLDUSDT": {
    "correlation": -0.14538858329421495,
    "abs_correlation": 0.14538858329421495,
    "data_points": 7,
    "volume_increase_on_price_up_pct": 33.33333333333333,
    "avg_volume_change_on_price_up": -6.202405819024428
  },
  "POLUSDT": {
    "correlation": -0.008641174232195348,
    "abs_correlation": 0.008641174232195348,
    "data_points": 7,
    "volume_increase_on_price_up_pct": 33.33333333333333,
    "avg_volume_change_on_price_up": 3.4106999607367703
  },
  "PAXGUSDT": {
    "correlation": 0.7625475452441092,
    "abs_correlation": 0.7625475452441092,
    "data_points": 7,
    "volume_increase_on_price_up_pct": 100.0,
    "avg_volume_change_on_price_up": 52.76223367380749
  },
  "USDTBUSDT": {
    "correlation": -0.0050282734791590655,
    "abs_correlation": 0.0050282734791590655,
    "data_points": 7,
    "volume_increase_on_price_up_pct": 25.0,
    "avg_volume_change_on_price_up": -21.65230389416031
  },
  "HASHUSDT": {
    "correlation": 0.1030369066300056,
    "abs_correlation": 0.1030369066300056,
    "data_points": 7,
    "volume_increase_on_price_up_pct": 100.0,
    "avg_volume_change_on_price_up": 100.92252145867751
  },
  "SYRUPUSDCUSDT": {
    "correlation": 0.6050665293358356,
    "abs_correlation": 0.6050665293358356,
    "data_points": 7,
    "volume_increase_on_price_up_pct": 50.0,
    "avg_volume_change_on_price_up": 93.04481791401703
  },
  "BFUSDUSDT": {
    "correlation": 0.5869164238398614,
    "abs_correlation": 0.5869164238398614,
    "data_points": 7,
    "volume_increase_on_price_up_pct": 50.0,
    "avg_volume_change_on_price_up": 12.894178509593162
  },
  "ALGOUSDT": {
    "correlation": -0.3042323255625551,
    "abs_correlation": 0.3042323255625551,
    "data_points": 7,
    "volume_increase_on_price_up_pct": 50.0,
    "avg_volume_change_on_price_up": -1.967971698075708
  },
  "TRUMPUSDT": {
    "correlation": -0.5749861365163026,
    "abs_correlation": 0.5749861365163026,
    "data_points": 7,
    "volume_increase_on_price_up_pct": 50.0,
    "avg_volume_change_on_price_up": -15.821057571127554
  },
  "RETHUSDT": {
    "correlation": 0.3142935751049232,
    "abs_correlation": 0.3142935751049232,
    "data_points": 7,
    "volume_increase_on_price_up_pct": 66.66666666666666,
    "avg_volume_change_on_price_up": 77.51294056002011
  },
  "RLUSDUSDT": {
    "correlation": 0.6319451438009019,
    "abs_correlation": 0.6319451438009019,
    "data_points": 7,
    "volume_increase_on_price_up_pct": 66.66666666666666,
    "avg_volume_change_on_price_up": 49.30133655940199
  },
  "KASUSDT": {
    "correlation": 0.3805796141100616,
    "abs_correlation": 0.3805796141100616,
    "data_points": 7,
    "volume_increase_on_price_up_pct": 100.0,
    "avg_volume_change_on_price_up": 27.130638914108683
  },
  "ARBUSDT": {
    "correlation": 0.2611699055133323,
    "abs_correlation": 0.2611699055133323,
    "data_points": 7,
    "volume_increase_on_price_up_pct": 33.33333333333333,
    "avg_volume_change_on_price_up": 20.234682378719825
  },
  "ATOMUSDT": {
    "correlation": 0.4381650642021503,
    "abs_correlation": 0.4381650642021503,
    "data_points": 7,
    "volume_increase_on_price_up_pct": 66.66666666666666,
    "avg_volume_change_on_price_up": 81.28504693784161
  },
  "USDGUSDT": {
    "correlation": 0.3080750967001669,
    "abs_correlation": 0.3080750967001669,
    "data_points": 7,
    "volume_increase_on_price_up_pct": 75.0,
    "avg_volume_change_on_price_up": 16.48710176177512
  },
  "GTUSDT": {
    "correlation": -0.003679306946232096,
    "abs_correlation": 0.003679306946232096,
    "data_points": 7,
    "volume_increase_on_price_up_pct": 50.0,
    "avg_volume_change_on_price_up": 3.938581199974793
  },
  "WBNBUSDT": {
    "correlation": -0.25740134572269224,
    "abs_correlation": 0.25740134572269224,
    "data_points": 7,
    "volume_increase_on_price_up_pct": 50.0,
    "avg_volume_change_on_price_up": -25.792391637502515
  },
  "USYCUSDT": {
    "correlation": -0.6740643334611235,
    "abs_correlation": 0.6740643334611235,
    "data_points": 6,
    "volume_increase_on_price_up_pct": 50.0,
    "avg_volume_change_on_price_up": 760.2179046644956
  },
  "BNSOLUSDT": {
    "correlation": 0.16426991841265223,
    "abs_correlation": 0.16426991841265223,
    "data_points": 7,
    "volume_increase_on_price_up_pct": 50.0,
    "avg_volume_change_on_price_up": 32.30344441603997
  },
  "FILUSDT": {
    "correlation": 0.03085382693070947,
    "abs_correlation": 0.03085382693070947,
    "data_points": 7,
    "volume_increase_on_price_up_pct": 100.0,
    "avg_volume_change_on_price_up": 35.810113417357506
  },
  "VETUSDT": {
    "correlation": 0.06370341400327781,
    "abs_correlation": 0.06370341400327781,
    "data_points": 7,
    "volume_increase_on_price_up_pct": 50.0,
    "avg_volume_change_on_price_up": 22.694866320377926
  },
  "QNTUSDT": {
    "correlation": -0.47265551467112726,
    "abs_correlation": 0.47265551467112726,
    "data_points": 7,
    "volume_increase_on_price_up_pct": 0.0,
    "avg_volume_change_on_price_up": -10.853931455230187
  },
  "FLRUSDT": {
    "correlation": 0.2510101986550719,
    "abs_correlation": 0.2510101986550719,
    "data_points": 7,
    "volume_increase_on_price_up_pct": 33.33333333333333,
    "avg_volume_change_on_price_up": 17.136772928518027
  },
  "RSETHUSDT": {
    "correlation": -0.266088437569873,
    "abs_correlation": 0.266088437569873,
    "data_points": 7,
    "volume_increase_on_price_up_pct": 33.33333333333333,
    "avg_volume_change_on_price_up": 42.63346071245831
  },
  "FBTCUSDT": {
    "correlation": 0.5058892972854022,
    "abs_correlation": 0.5058892972854022,
    "data_points": 7,
    "volume_increase_on_price_up_pct": 100.0,
    "avg_volume_change_on_price_up": 157.44233618234975
  },
  "XDCUSDT": {
    "correlation": 0.3423528093823719,
    "abs_correlation": 0.3423528093823719,
    "data_points": 7,
    "volume_increase_on_price_up_pct": 60.0,
    "avg_volume_change_on_price_up": 7.20702869108926
  },
  "SKYUSDT": {
    "correlation": -0.5935397773031111,
    "abs_correlation": 0.5935397773031111,
    "data_points": 7,
    "volume_increase_on_price_up_pct": 50.0,
    "avg_volume_change_on_price_up": 0.12956528330421158
  }
}