{
  "BTCUSDT": {
    "correlation": 0.15181572187386141,
    "abs_correlation": 0.15181572187386141,
    "data_points": 7,
    "volume_increase_on_price_up_pct": 100.0,
    "avg_volume_change_on_price_up": 26.82691463028086
  },
  "ETHUSDT": {
    "correlation": 0.33476598452494044,
    "abs_correlation": 0.33476598452494044,
    "data_points": 7,
    "volume_increase_on_price_up_pct": 75.0,
    "avg_volume_change_on_price_up": 5.6659168910354705
  },
  "USDTUSDT": {
    "correlation": 0.2898488327983049,
    "abs_correlation": 0.2898488327983049,
    "data_points": 7,
    "volume_increase_on_price_up_pct": 80.0,
    "avg_volume_change_on_price_up": 5.302252521884889
  },
  "XRPUSDT": {
    "correlation": 0.3703879204725622,
    "abs_correlation": 0.3703879204725622,
    "data_points": 7,
    "volume_increase_on_price_up_pct": 50.0,
    "avg_volume_change_on_price_up": 3.796933865746216
  },
  "BNBUSDT": {
    "correlation": -0.09473750647221887,
    "abs_correlation": 0.09473750647221887,
    "data_points": 7,
    "volume_increase_on_price_up_pct": 25.0,
    "avg_volume_change_on_price_up": -8.337535571265864
  },
  "SOLUSDT": {
    "correlation": 0.38259733293001535,
    "abs_correlation": 0.38259733293001535,
    "data_points": 7,
    "volume_increase_on_price_up_pct": 100.0,
    "avg_volume_change_on_price_up": 24.679546675062603
  },
  "USDCUSDT": {
    "correlation": 0.5524842996076856,
    "abs_correlation": 0.5524842996076856,
    "data_points": 7,
    "volume_increase_on_price_up_pct": 50.0,
    "avg_volume_change_on_price_up": 15.86190822791121
  },
  "TRXUSDT": {
    "correlation": -0.08774252815338858,
    "abs_correlation": 0.08774252815338858,
    "data_points": 7,
    "volume_increase_on_price_up_pct": 50.0,
    "avg_volume_change_on_price_up": 3.3186224779887254
  },
  "STETHUSDT": {
    "correlation": -0.15314636867646986,
    "abs_correlation": 0.15314636867646986,
    "data_points": 7,
    "volume_increase_on_price_up_pct": 25.0,
    "avg_volume_change_on_price_up": -22.712909874266007
  },
  "DOGEUSDT": {
    "correlation": -0.1576299874943473,
    "abs_correlation": 0.1576299874943473,
    "data_points": 7,
    "volume_increase_on_price_up_pct": 25.0,
    "avg_volume_change_on_price_up": -10.16523586904266
  },
  "ADAUSDT": {
    "correlation": -0.19524822842040407,
    "abs_correlation": 0.19524822842040407,
    "data_points": 7,
    "volume_increase_on_price_up_pct": 33.33333333333333,
    "avg_volume_change_on_price_up": 2.3111217093559002
  },
  "FIGR_HELOCUSDT": {
    "correlation": -0.05285127910722043,
    "abs_correlation": 0.05285127910722043,
    "data_points": 7,
    "volume_increase_on_price_up_pct": 50.0,
    "avg_volume_change_on_price_up": 43.92565013290307
  },
  "WBTUSDT": {
    "correlation": 0.7183497284245688,
    "abs_correlation": 0.7183497284245688,
    "data_points": 7,
    "volume_increase_on_price_up_pct": 100.0,
    "avg_volume_change_on_price_up": 50.00045882743772
  },
  "WSTETHUSDT": {
    "correlation": -0.019889779352191224,
    "abs_correlation": 0.019889779352191224,
    "data_points": 7,
    "volume_increase_on_price_up_pct": 75.0,
    "avg_volume_change_on_price_up": 7.019743406737653
  },
  "BCHUSDT": {
    "correlation": 0.8654731394499836,
    "abs_correlation": 0.8654731394499836,
    "data_points": 7,
    "volume_increase_on_price_up_pct": 50.0,
    "avg_volume_change_on_price_up": 44.991284908773835
  },
  "WBTCUSDT": {
    "correlation": -0.028164490018829216,
    "abs_correlation": 0.028164490018829216,
    "data_points": 7,
    "volume_increase_on_price_up_pct": 100.0,
    "avg_volume_change_on_price_up": 20.134921284603145
  },
  "WBETHUSDT": {
    "correlation": 0.6770198414910721,
    "abs_correlation": 0.6770198414910721,
    "data_points": 7,
    "volume_increase_on_price_up_pct": 75.0,
    "avg_volume_change_on_price_up": 130.66525680427313
  },
  "ZECUSDT": {
    "correlation": -0.6101218078571726,
    "abs_correlation": 0.6101218078571726,
    "data_points": 7,
    "volume_increase_on_price_up_pct": 33.33333333333333,
    "avg_volume_change_on_price_up": -14.249564241856403
  },
  "LINKUSDT": {
    "correlation": -0.2104773020117152,
    "abs_correlation": 0.2104773020117152,
    "data_points": 7,
    "volume_increase_on_price_up_pct": 50.0,
    "avg_volume_change_on_price_up": -7.581928663541332
  },
  "USDSUSDT": {
    "correlation": 0.353058329293948,
    "abs_correlation": 0.353058329293948,
    "data_points": 7,
    "volume_increase_on_price_up_pct": 75.0,
    "avg_volume_change_on_price_up": 233.9390769860165
  },
  "BSC-USDUSDT": {
    "correlation": -0.7159088652558233,
    "abs_correlation": 0.7159088652558233,
    "data_points": 7,
    "volume_increase_on_price_up_pct": 25.0,
    "avg_volume_change_on_price_up": -15.839157321383224
  },
  "HYPEUSDT": {
    "correlation": -0.2020049967055586,
    "abs_correlation": 0.2020049967055586,
    "data_points": 7,
    "volume_increase_on_price_up_pct": 50.0,
    "avg_volume_change_on_price_up": -0.6867860990851402
  },
  "LEOUSDT": {
    "correlation": 0.07864737265197978,
    "abs_correlation": 0.07864737265197978,
    "data_points": 7,
    "volume_increase_on_price_up_pct": 60.0,
    "avg_volume_change_on_price_up": 26.20737308286842
  },
  "XLMUSDT": {
    "correlation": 0.27464670397554264,
    "abs_correlation": 0.27464670397554264,
    "data_points": 7,
    "volume_increase_on_price_up_pct": 66.66666666666666,
    "avg_volume_change_on_price_up": 23.30059665882708
  },
  "WETHUSDT": {
    "correlation": 0.3037416454626944,
    "abs_correlation": 0.3037416454626944,
    "data_points": 7,
    "volume_increase_on_price_up_pct": 50.0,
    "avg_volume_change_on_price_up": 2.855678687340099
  },
  "WEETHUSDT": {
    "correlation": 0.2374586977601879,
    "abs_correlation": 0.2374586977601879,
    "data_points": 7,
    "volume_increase_on_price_up_pct": 75.0,
    "avg_volume_change_on_price_up": 109.88273803445017
  },
  "USDEUSDT": {
    "correlation": 0.5596481401939526,
    "abs_correlation": 0.5596481401939526,
    "data_points": 7,
    "volume_increase_on_price_up_pct": 50.0,
    "avg_volume_change_on_price_up": 4.678882813746534
  },
  "XMRUSDT": {
    "correlation": -0.058312766401414376,
    "abs_correlation": 0.058312766401414376,
    "data_points": 7,
    "volume_increase_on_price_up_pct": 50.0,
    "avg_volume_change_on_price_up": 3.6243582110459722
  },
  "LTCUSDT": {
    "correlation": -0.07760869890553435,
    "abs_correlation": 0.07760869890553435,
    "data_points": 7,
    "volume_increase_on_price_up_pct": 100.0,
    "avg_volume_change_on_price_up": 10.360629927501448
  },
  "CBBTCUSDT": {
    "correlation": 0.1570398021936127,
    "abs_correlation": 0.1570398021936127,
    "data_points": 7,
    "volume_increase_on_price_up_pct": 100.0,
    "avg_volume_change_on_price_up": 29.40578531262939
  },
  "HBARUSDT": {
    "correlation": 0.6499644664277789,
    "abs_correlation": 0.6499644664277789,
    "data_points": 7,
    "volume_increase_on_price_up_pct": 25.0,
    "avg_volume_change_on_price_up": 24.108889600173132
  },
  "AVAXUSDT": {
    "correlation": 0.30470083020248656,
    "abs_correlation": 0.30470083020248656,
    "data_points": 7,
    "volume_increase_on_price_up_pct": 33.33333333333333,
    "avg_volume_change_on_price_up": 8.603048184776828
  },
  "SUIUSDT": {
    "correlation": 0.35226262265896835,
    "abs_correlation": 0.35226262265896835,
    "data_points": 7,
    "volume_increase_on_price_up_pct": 33.33333333333333,
    "avg_volume_change_on_price_up": 20.21360591178358
  },
  "SHIBUSDT": {
    "correlation": -0.022098634232263204,
    "abs_correlation": 0.022098634232263204,
    "data_points": 7,
    "volume_increase_on_price_up_pct": 33.33333333333333,
    "avg_volume_change_on_price_up": 8.88420398740471
  },
  "DAIUSDT": {
    "correlation": 0.05637076315876968,
    "abs_correlation": 0.05637076315876968,
    "data_points": 7,
    "volume_increase_on_price_up_pct": 75.0,
    "avg_volume_change_on_price_up": 30.77778376588921
  },
  "SUSDEUSDT": {
    "correlation": 0.33036349776503365,
    "abs_correlation": 0.33036349776503365,
    "data_points": 7,
    "volume_increase_on_price_up_pct": 60.0,
    "avg_volume_change_on_price_up": 7.411115081442852
  },
  "WLFIUSDT": {
    "correlation": 0.665822686076914,
    "abs_correlation": 0.665822686076914,
    "data_points": 7,
    "volume_increase_on_price_up_pct": 40.0,
    "avg_volume_change_on_price_up": 34.425680929240244
  },
  "CROUSDT": {
    "correlation": 0.3181365694535764,
    "abs_correlation": 0.3181365694535764,
    "data_points": 7,
    "volume_increase_on_price_up_pct": 50.0,
    "avg_volume_change_on_price_up": 15.728003829190806
  },
  "UNIUSDT": {
    "correlation": 0.4065341580653716,
    "abs_correlation": 0.4065341580653716,
    "data_points": 7,
    "volume_increase_on_price_up_pct": 50.0,
    "avg_volume_change_on_price_up": 5.433842699249758
  },
  "TONUSDT": {
    "correlation": -0.029615103057726144,
    "abs_correlation": 0.029615103057726144,
    "data_points": 7,
    "volume_increase_on_price_up_pct": 33.33333333333333,
    "avg_volume_change_on_price_up": -5.900167822656962
  },
  "USDT0USDT": {
    "correlation": 0.45872330966695046,
    "abs_correlation": 0.45872330966695046,
    "data_points": 7,
    "volume_increase_on_price_up_pct": 100.0,
    "avg_volume_change_on_price_up": 39.69698457547597
  },
  "DOTUSDT": {
    "correlation": 0.12637798929446872,
    "abs_correlation": 0.12637798929446872,
    "data_points": 7,
    "volume_increase_on_price_up_pct": 50.0,
    "avg_volume_change_on_price_up": 19.572158184367215
  },
  "SUSDSUSDT": {
    "correlation": 0.5180621847934623,
    "abs_correlation": 0.5180621847934623,
    "data_points": 7,
    "volume_increase_on_price_up_pct": 75.0,
    "avg_volume_change_on_price_up": 52.21107147011843
  },
  "PYUSDUSDT": {
    "correlation": 0.613695590783556,
    "abs_correlation": 0.613695590783556,
    "data_points": 7,
    "volume_increase_on_price_up_pct": 50.0,
    "avg_volume_change_on_price_up": 15.120048513581958
  },
  "MNTUSDT": {
    "correlation": -0.7420269725896877,
    "abs_correlation": 0.7420269725896877,
    "data_points": 7,
    "volume_increase_on_price_up_pct": 40.0,
    "avg_volume_change_on_price_up": -5.652348489438197
  },
  "MUSDT": {
    "correlation": 0.32589852288723636,
    "abs_correlation": 0.32589852288723636,
    "data_points": 7,
    "volume_increase_on_price_up_pct": 100.0,
    "avg_volume_change_on_price_up": 2.231782258040387
  },
  "CCUSDT": {
    "correlation": 0.3553904116291819,
    "abs_correlation": 0.3553904116291819,
    "data_points": 7,
    "volume_increase_on_price_up_pct": 50.0,
    "avg_volume_change_on_price_up": 185.45812252326564
  },
  "TAOUSDT": {
    "correlation": 0.2703575802815801,
    "abs_correlation": 0.2703575802815801,
    "data_points": 7,
    "volume_increase_on_price_up_pct": 100.0,
    "avg_volume_change_on_price_up": 30.437021546206584
  },
  "AAVEUSDT": {
    "correlation": 0.09569317138977332,
    "abs_correlation": 0.09569317138977332,
    "data_points": 7,
    "volume_increase_on_price_up_pct": 50.0,
    "avg_volume_change_on_price_up": -0.2499075565989134
  },
  "USD1USDT": {
    "correlation": 0.8323285915212828,
    "abs_correlation": 0.8323285915212828,
    "data_points": 7,
    "volume_increase_on_price_up_pct": 100.0,
    "avg_volume_change_on_price_up": 12.52570637979714
  },
  "NEARUSDT": {
    "correlation": 0.3345580900196021,
    "abs_correlation": 0.3345580900196021,
    "data_points": 7,
    "volume_increase_on_price_up_pct": 66.66666666666666,
    "avg_volume_change_on_price_up": 21.662292361725918
  },
  "BGBUSDT": {
    "correlation": -0.8551788680018138,
    "abs_correlation": 0.8551788680018138,
    "data_points": 7,
    "volume_increase_on_price_up_pct": 0.0,
    "avg_volume_change_on_price_up": -18.64682714899171
  },
  "BUIDLUSDT": {
    "correlation": 0.0,
    "abs_correlation": 0.0,
    "data_points": 7,
    "volume_increase_on_price_up_pct": 0.0,
    "avg_volume_change_on_price_up": 0.0
  },
  "ICPUSDT": {
    "correlation": 0.4481827350131038,
    "abs_correlation": 0.4481827350131038,
    "data_points": 7,
    "volume_increase_on_price_up_pct": 50.0,
    "avg_volume_change_on_price_up": 15.843314138906624
  },
  "ASTERUSDT": {
    "correlation": 0.18555725270225631,
    "abs_correlation": 0.18555725270225631,
    "data_points": 7,
    "volume_increase_on_price_up_pct": 66.66666666666666,
    "avg_volume_change_on_price_up": 5.18593711465634
  },
  "OKBUSDT": {
    "correlation": -0.5913164143639069,
    "abs_correlation": 0.5913164143639069,
    "data_points": 7,
    "volume_increase_on_price_up_pct": 25.0,
    "avg_volume_change_on_price_up": -12.49976500962044
  },
  "ETCUSDT": {
    "correlation": 0.15067752585329394,
    "abs_correlation": 0.15067752585329394,
    "data_points": 7,
    "volume_increase_on_price_up_pct": 50.0,
    "avg_volume_change_on_price_up": 10.011584540992313
  },
  "USDFUSDT": {
    "correlation": -0.0596572027019588,
    "abs_correlation": 0.0596572027019588,
    "data_points": 7,
    "volume_increase_on_price_up_pct": 100.0,
    "avg_volume_change_on_price_up": 108.07425392624181
  },
  "XAUTUSDT": {
    "correlation": 0.5057854981978659,
    "abs_correlation": 0.5057854981978659,
    "data_points": 7,
    "volume_increase_on_price_up_pct": 75.0,
    "avg_volume_change_on_price_up": 17.12766775011926
  },
  "PIUSDT": {
    "correlation": 0.5246804846288744,
    "abs_correlation": 0.5246804846288744,
    "data_points": 7,
    "volume_increase_on_price_up_pct": 40.0,
    "avg_volume_change_on_price_up": 15.165151842949959
  },
  "JITOSOLUSDT": {
    "correlation": 0.255877882438775,
    "abs_correlation": 0.255877882438775,
    "data_points": 7,
    "volume_increase_on_price_up_pct": 66.66666666666666,
    "avg_volume_change_on_price_up": 17.62839929935265
  },
  "PEPEUSDT": {
    "correlation": -0.1303074310846371,
    "abs_correlation": 0.1303074310846371,
    "data_points": 7,
    "volume_increase_on_price_up_pct": 25.0,
    "avg_volume_change_on_price_up": -8.90332013813271
  },
  "ENAUSDT": {
    "correlation": 0.5232996138344602,
    "abs_correlation": 0.5232996138344602,
    "data_points": 7,
    "volume_increase_on_price_up_pct": 66.66666666666666,
    "avg_volume_change_on_price_up": 26.69670997961396
  },
  "JLPUSDT": {
    "correlation": 0.12337945906045583,
    "abs_correlation": 0.12337945906045583,
    "data_points": 7,
    "volume_increase_on_price_up_pct": 66.66666666666666,
    "avg_volume_change_on_price_up": 23.180505419620665
  },
  "RAINUSDT": {
    "correlation": 0.9787312401726389,
    "abs_correlation": 0.9787312401726389,
    "data_points": 7,
    "volume_increase_on_price_up_pct": 60.0,
    "avg_volume_change_on_price_up": 70.77743200829768
  },
  "APTUSDT": {
    "correlation": -0.48235285867452854,
    "abs_correlation": 0.48235285867452854,
    "data_points": 7,
    "volume_increase_on_price_up_pct": 66.66666666666666,
    "avg_volume_change_on_price_up": -2.0275964393479886
  },
  "PUMPUSDT": {
    "correlation": -0.0656468302950707,
    "abs_correlation": 0.0656468302950707,
    "data_points": 7,
    "volume_increase_on_price_up_pct": 66.66666666666666,
    "avg_volume_change_on_price_up": -1.97713395501119
  },
  "HTXUSDT": {
    "correlation": -0.6555929387935909,
    "abs_correlation": 0.6555929387935909,
    "data_points": 7,
    "volume_increase_on_price_up_pct": 0.0,
    "avg_volume_change_on_price_up": -20.993141687379048
  },
  "ONDOUSDT": {
    "correlation": -0.13029429150104943,
    "abs_correlation": 0.13029429150104943,
    "data_points": 7,
    "volume_increase_on_price_up_pct": 66.66666666666666,
    "avg_volume_change_on_price_up": 10.88043966250756
  },
  "KCSUSDT": {
    "correlation": 0.3061907514071663,
    "abs_correlation": 0.3061907514071663,
    "data_points": 7,
    "volume_increase_on_price_up_pct": 50.0,
    "avg_volume_change_on_price_up": 13.668059043547338
  },
  "WLDUSDT": {
    "correlation": -0.18250215880071433,
    "abs_correlation": 0.18250215880071433,
    "data_points": 7,
    "volume_increase_on_price_up_pct": 50.0,
    "avg_volume_change_on_price_up": -6.950279999083213
  },
  "POLUSDT": {
    "correlation": 0.1308615456212975,
    "abs_correlation": 0.1308615456212975,
    "data_points": 7,
    "volume_increase_on_price_up_pct": 50.0,
    "avg_volume_change_on_price_up": 2.8195254492355577
  },
  "PAXGUSDT": {
    "correlation": 0.5739468579654714,
    "abs_correlation": 0.5739468579654714,
    "data_points": 7,
    "volume_increase_on_price_up_pct": 75.0,
    "avg_volume_change_on_price_up": 43.68622146897611
  },
  "USDTBUSDT": {
    "correlation": 0.1900661953689439,
    "abs_correlation": 0.1900661953689439,
    "data_points": 7,
    "volume_increase_on_price_up_pct": 0.0,
    "avg_volume_change_on_price_up": -31.59332753665996
  },
  "BFUSDUSDT": {
    "correlation": 0.6159003318856896,
    "abs_correlation": 0.6159003318856896,
    "data_points": 7,
    "volume_increase_on_price_up_pct": 50.0,
    "avg_volume_change_on_price_up": 17.719943318081306
  },
  "SYRUPUSDCUSDT": {
    "correlation": 0.6220288829832981,
    "abs_correlation": 0.6220288829832981,
    "data_points": 7,
    "volume_increase_on_price_up_pct": 60.0,
    "avg_volume_change_on_price_up": 98.47233504348016
  },
  "ALGOUSDT": {
    "correlation": -0.12159876501227385,
    "abs_correlation": 0.12159876501227385,
    "data_points": 7,
    "volume_increase_on_price_up_pct": 33.33333333333333,
    "avg_volume_change_on_price_up": 16.184795264111827
  },
  "RETHUSDT": {
    "correlation": 0.11063173888747675,
    "abs_correlation": 0.11063173888747675,
    "data_points": 7,
    "volume_increase_on_price_up_pct": 50.0,
    "avg_volume_change_on_price_up": 38.774654972968555
  },
  "TRUMPUSDT": {
    "correlation": -0.4845415981865353,
    "abs_correlation": 0.4845415981865353,
    "data_points": 7,
    "volume_increase_on_price_up_pct": 33.33333333333333,
    "avg_volume_change_on_price_up": -12.647369365070668
  },
  "ARBUSDT": {
    "correlation": 0.26574014690387165,
    "abs_correlation": 0.26574014690387165,
    "data_points": 7,
    "volume_increase_on_price_up_pct": 33.33333333333333,
    "avg_volume_change_on_price_up": 21.34803845866103
  },
  "HASHUSDT": {
    "correlation": 0.3060918423588894,
    "abs_correlation": 0.3060918423588894,
    "data_points": 7,
    "volume_increase_on_price_up_pct": 100.0,
    "avg_volume_change_on_price_up": 185.25252120512593
  },
  "BNSOLUSDT": {
    "correlation": 0.22154284825911363,
    "abs_correlation": 0.22154284825911363,
    "data_points": 7,
    "volume_increase_on_price_up_pct": 66.66666666666666,
    "avg_volume_change_on_price_up": 32.760786873521994
  },
  "ATOMUSDT": {
    "correlation": 0.4171349679692048,
    "abs_correlation": 0.4171349679692048,
    "data_points": 7,
    "volume_increase_on_price_up_pct": 66.66666666666666,
    "avg_volume_change_on_price_up": 84.6646660925502
  },
  "FILUSDT": {
    "correlation": 0.09821708381666376,
    "abs_correlation": 0.09821708381666376,
    "data_points": 7,
    "volume_increase_on_price_up_pct": 100.0,
    "avg_volume_change_on_price_up": 33.35131859342969
  },
  "WBNBUSDT": {
    "correlation": -0.11651373928808316,
    "abs_correlation": 0.11651373928808316,
    "data_points": 7,
    "volume_increase_on_price_up_pct": 50.0,
    "avg_volume_change_on_price_up": -4.246331211453744
  },
  "USDGUSDT": {
    "correlation": 0.13819334630681523,
    "abs_correlation": 0.13819334630681523,
    "data_points": 7,
    "volume_increase_on_price_up_pct": 66.66666666666666,
    "avg_volume_change_on_price_up": 12.978583776616137
  },
  "VETUSDT": {
    "correlation": 0.11159160130572568,
    "abs_correlation": 0.11159160130572568,
    "data_points": 7,
    "volume_increase_on_price_up_pct": 33.33333333333333,
    "avg_volume_change_on_price_up": 15.319327214469206
  },
  "USYCUSDT": {
    "correlation": -0.5392970434899619,
    "abs_correlation": 0.5392970434899619,
    "data_points": 6,
    "volume_increase_on_price_up_pct": 50.0,
    "avg_volume_change_on_price_up": 760.2179058881254
  },
  "GTUSDT": {
    "correlation": -0.15570782075152884,
    "abs_correlation": 0.15570782075152884,
    "data_points": 7,
    "volume_increase_on_price_up_pct": 50.0,
    "avg_volume_change_on_price_up": -7.073328040873362
  },
  "KASUSDT": {
    "correlation": 0.2806071056208548,
    "abs_correlation": 0.2806071056208548,
    "data_points": 7,
    "volume_increase_on_price_up_pct": 100.0,
    "avg_volume_change_on_price_up": 26.311314799635184
  },
  "RLUSDUSDT": {
    "correlation": 0.6404521136863243,
    "abs_correlation": 0.6404521136863243,
    "data_points": 7,
    "volume_increase_on_price_up_pct": 66.66666666666666,
    "avg_volume_change_on_price_up": 49.30133655940199
  },
  "QNTUSDT": {
    "correlation": -0.4443898334954299,
    "abs_correlation": 0.4443898334954299,
    "data_points": 7,
    "volume_increase_on_price_up_pct": 25.0,
    "avg_volume_change_on_price_up": -9.236384295202464
  },
  "FLRUSDT": {
    "correlation": 0.23323494004619993,
    "abs_correlation": 0.23323494004619993,
    "data_points": 7,
    "volume_increase_on_price_up_pct": 50.0,
    "avg_volume_change_on_price_up": 25.254834716046513
  },
  "RSETHUSDT": {
    "correlation": -0.2967422593932553,
    "abs_correlation": 0.2967422593932553,
    "data_points": 7,
    "volume_increase_on_price_up_pct": 50.0,
    "avg_volume_change_on_price_up": 58.80861205817456
  },
  "FBTCUSDT": {
    "correlation": 0.5815783664350908,
    "abs_correlation": 0.5815783664350908,
    "data_points": 7,
    "volume_increase_on_price_up_pct": 66.66666666666666,
    "avg_volume_change_on_price_up": 100.69537585481727
  },
  "LBTCUSDT": {
    "correlation": 0.03720561442652927,
    "abs_correlation": 0.03720561442652927,
    "data_points": 7,
    "volume_increase_on_price_up_pct": 66.66666666666666,
    "avg_volume_change_on_price_up": 17.005586992820806
  },
  "SKYUSDT": {
    "correlation": -0.4290305695497817,
    "abs_correlation": 0.4290305695497817,
    "data_points": 7,
    "volume_increase_on_price_up_pct": 66.66666666666666,
    "avg_volume_change_on_price_up": 2.044953021913452
  }
}